docs/Makefile
docs/conf.py
docs/index.rst
docs/make.bat
docs/requirements.txt
docs/api/e3nn.rst
docs/api/io/cartesian_tensor.rst
docs/api/io/io.rst
docs/api/io/spherical_tensor.rst
docs/api/math/math.rst
docs/api/nn/nn.rst
docs/api/nn/nn_bn.rst
docs/api/nn/nn_fc.rst
docs/api/nn/nn_gate.rst
docs/api/nn/nn_normact.rst
docs/api/nn/nn_s2act.rst
docs/api/nn/models/gate_points_2101.rst
docs/api/nn/models/graph.svg
docs/api/nn/models/models.rst
docs/api/nn/models/v2103.rst
docs/api/o3/o3.rst
docs/api/o3/o3_irreps.rst
docs/api/o3/o3_reduce.rst
docs/api/o3/o3_rotation.rst
docs/api/o3/o3_s2grid.rst
docs/api/o3/o3_sh.rst
docs/api/o3/o3_tp.rst
docs/api/o3/o3_wigner.rst
docs/api/util/jit.rst
docs/api/util/test.rst
docs/api/util/util.rst
docs/examples/examples.rst
docs/examples/tetris_gate.rst
docs/examples/tetris_polynomial.rst
docs/guide/change_of_basis.rst
docs/guide/convolution.rst
docs/guide/equivar_testing.rst
docs/guide/guide.rst
docs/guide/installation.md
docs/guide/irreps.rst
docs/guide/jit.rst
docs/guide/normalization.rst
docs/guide/periodic_boundary_conditions.rst
docs/guide/transformer.png
docs/guide/transformer.rst
e3nn/__init__.py
e3nn/io/__init__.py
e3nn/io/_cartesian_tensor.py
e3nn/io/_spherical_tensor.py
e3nn/math/__init__.py
e3nn/math/_bessel.py
e3nn/math/_linalg.py
e3nn/math/_normalize_activation.py
e3nn/math/_reduce.py
e3nn/math/_soft_one_hot_linspace.py
e3nn/math/_soft_unit_step.py
e3nn/math/perm.py
e3nn/nn/__init__.py
e3nn/nn/_activation.py
e3nn/nn/_batchnorm.py
e3nn/nn/_dropout.py
e3nn/nn/_extract.py
e3nn/nn/_fc.py
e3nn/nn/_gate.py
e3nn/nn/_identity.py
e3nn/nn/_normact.py
e3nn/nn/_s2act.py
e3nn/nn/_so3act.py
e3nn/nn/models/__init__.py
e3nn/nn/models/gate_points_2101.py
e3nn/nn/models/gate_points_2102.py
e3nn/nn/models/v2103/__init__.py
e3nn/nn/models/v2103/conv_points_in_out.py
e3nn/nn/models/v2103/gate_points_message_passing.py
e3nn/nn/models/v2103/gate_points_networks.py
e3nn/nn/models/v2103/points_convolution.py
e3nn/nn/models/v2103/voxel_convolution.py
e3nn-0.5.9.dist-info/licenses/LICENSE
e3nn-0.5.9.dist-info/METADATA
e3nn-0.5.9.dist-info/WHEEL
e3nn-0.5.9.dist-info/top_level.txt
e3nn-0.5.9.dist-info/RECORD
