Metadata-Version: 2.4
Name: e3nn
Version: 0.5.9
Summary: Equivariant convolutional neural networks for the group E(3) of 3 dimensional rotations, translations, and mirrors.
License: MIT
Project-URL: homepage, https://e3nn.org
Project-URL: documentation, https://docs.e3nn.org/
Project-URL: repository, https://github.com/e3nn/e3nn.git
Project-URL: changelog, https://github.com/e3nn/e3nn/blob/main/.github/CHANGELOG.md
Classifier: Programming Language :: Python
Classifier: Programming Language :: Python :: 3
Classifier: Programming Language :: Python :: 3 :: Only
Classifier: Programming Language :: Python :: 3.7
Classifier: Programming Language :: Python :: 3.8
Classifier: Programming Language :: Python :: 3.9
Classifier: Programming Language :: Python :: 3.10
Classifier: License :: OSI Approved :: MIT License
Classifier: Operating System :: POSIX
Classifier: Operating System :: MacOS
Requires-Python: >=3.7
License-File: LICENSE
Requires-Dist: sympy
Requires-Dist: scipy
Requires-Dist: torch>=1.8.0
Requires-Dist: opt_einsum_fx>=0.1.4
Provides-Extra: dev
Requires-Dist: pytest; extra == "dev"
Requires-Dist: pre-commit; extra == "dev"
Dynamic: license-file
